pyihome/__init__.py
pyihome/pyihome.py
pyihome-0.0.2.dist-info/METADATA
pyihome-0.0.2.dist-info/RECORD
pyihome-0.0.2.dist-info/WHEEL
pyihome-0.0.2.dist-info/top_level.txt
