Metadata-Version: 2.1
Name: pyihome
Version: 0.0.2
Summary: Python library to interface with iHome API.
Home-page: https://github.com/lmelvin/pyihome
Author: lmelvin
Author-email: luke@lucasmelvin.com
License: UNKNOWN
Platform: UNKNOWN
Classifier: Programming Language :: Python :: 3.6
Classifier: License :: OSI Approved :: MIT License
Classifier: Operating System :: OS Independent
